quick_postman-0.1.0.dist-info/METADATA
quick_postman-0.1.0.dist-info/WHEEL
quick_postman-0.1.0.dist-info/entry_points.txt
quick_postman/__init__.py
quick_postman/mail.py
quick_postman-0.1.0.dist-info/RECORD
