Metadata-Version: 2.1
Name: quick-postman
Version: 0.1.0
Summary: A quick mail sender, postman
Author-Email: svtter <svtter@qq.com>
License: MIT
Requires-Python: >=3.10
Requires-Dist: python-dotenv>=1.0.1
